test.cpython-38-darwin.so
cygraph/__init__.py
cygraph/algorithms/__init__.pxd
cygraph/algorithms/__init__.py
cygraph/algorithms/articulation_points.c
cygraph/algorithms/articulation_points.cpython-38-darwin.so
cygraph/algorithms/articulation_points.pxd
cygraph/algorithms/articulation_points.pyx
cygraph/algorithms/components.c
cygraph/algorithms/components.cpython-38-darwin.so
cygraph/algorithms/components.pxd
cygraph/algorithms/components.pyx
cygraph/algorithms/partitioning.c
cygraph/algorithms/partitioning.cpython-38-darwin.so
cygraph/algorithms/partitioning.pxd
cygraph/algorithms/partitioning.pyx
cygraph/algorithms/shortest_path.c
cygraph/algorithms/shortest_path.cpython-38-darwin.so
cygraph/algorithms/shortest_path.pxd
cygraph/algorithms/shortest_path.pyx
cygraph/graph_/__init__.pxd
cygraph/graph_/__init__.py
cygraph/graph_/dynamic_graph.c
cygraph/graph_/dynamic_graph.cpython-38-darwin.so
cygraph/graph_/dynamic_graph.pxd
cygraph/graph_/dynamic_graph.pyx
cygraph/graph_/graph.c
cygraph/graph_/graph.cpython-38-darwin.so
cygraph/graph_/graph.pxd
cygraph/graph_/graph.pyx
cygraph/graph_/static_graph.c
cygraph/graph_/static_graph.cpython-38-darwin.so
cygraph/graph_/static_graph.pxd
cygraph/graph_/static_graph.pyx
cygraph-0.2.1.dist-info/LICENSE
cygraph-0.2.1.dist-info/METADATA
cygraph-0.2.1.dist-info/WHEEL
cygraph-0.2.1.dist-info/top_level.txt
cygraph-0.2.1.dist-info/RECORD
