Metadata-Version: 2.1
Name: cygraph
Version: 0.2.1
Summary: A graph theory library written in Cython
Home-page: https://github.com/lol-cubes/cygraph
Author: Arin Khare
Author-email: arinmkhare@gmail.com
License: UNKNOWN
Platform: UNKNOWN
Requires-Dist: numpy (>=1.19.0)
